{
  "main": {
    "id": "59431d4b73d5f665",
    "type": "split",
    "children": [
      {
        "id": "ddb4bfcdb8dfbfe8",
        "type": "tabs",
        "children": [
          {
            "id": "3cf91371da09bdd5",
            "type": "leaf",
            "state": {
              "type": "graph",
              "state": {},
              "icon": "lucide-git-fork",
              "title": "Visualização em gráfico"
            }
          },
          {
            "id": "36cd94e2515277a8",
            "type": "leaf",
            "state": {
              "type": "graph",
              "state": {},
              "icon": "lucide-git-fork",
              "title": "Visualização em gráfico"
            }
          }
        ]
      }
    ],
    "direction": "vertical"
  },
  "left": {
    "id": "d0870ddb9c2ea576",
    "type": "split",
    "children": [
      {
        "id": "268727b99bdc5aea",
        "type": "tabs",
        "children": [
          {
            "id": "c7714e091bf0d6dc",
            "type": "leaf",
            "state": {
              "type": "file-explorer",
              "state": {
                "sortOrder": "alphabetical",
                "autoReveal": false
              },
              "icon": "lucide-folder-closed",
              "title": "Explorador de arquivos"
            }
          },
          {
            "id": "9e9a8f0425f7497e",
            "type": "leaf",
            "state": {
              "type": "search",
              "state": {
                "query": "",
                "matchingCase": false,
                "explainSearch": false,
                "collapseAll": false,
                "extraContext": false,
                "sortOrder": "alphabetical"
              },
              "icon": "lucide-search",
              "title": "Procurar"
            }
          },
          {
            "id": "9c805c46fbf25325",
            "type": "leaf",
            "state": {
              "type": "bookmarks",
              "state": {},
              "icon": "lucide-bookmark",
              "title": "Marcadores"
            }
          }
        ]
      }
    ],
    "direction": "horizontal",
    "width": 300
  },
  "right": {
    "id": "6671fe0e0f4b64b6",
    "type": "split",
    "children": [
      {
        "id": "f7b82b3933f9cb53",
        "type": "tabs",
        "children": [
          {
            "id": "f71cb407d2b928a3",
            "type": "leaf",
            "state": {
              "type": "backlink",
              "state": {
                "collapseAll": false,
                "extraContext": false,
                "sortOrder": "alphabetical",
                "showSearch": false,
                "searchQuery": "",
                "backlinkCollapsed": false,
                "unlinkedCollapsed": true
              },
              "icon": "links-coming-in",
              "title": "Links inversos"
            }
          },
          {
            "id": "6a3cec885f8b33c0",
            "type": "leaf",
            "state": {
              "type": "outgoing-link",
              "state": {
                "linksCollapsed": false,
                "unlinkedCollapsed": true
              },
              "icon": "links-going-out",
              "title": "Links de saída"
            }
          },
          {
            "id": "db0ceaf9cdafc100",
            "type": "leaf",
            "state": {
              "type": "tag",
              "state": {
                "sortOrder": "frequency",
                "useHierarchy": true,
                "showSearch": false,
                "searchQuery": ""
              },
              "icon": "lucide-tags",
              "title": "Etiquetas"
            }
          },
          {
            "id": "c14d7ea0a4c81d18",
            "type": "leaf",
            "state": {
              "type": "all-properties",
              "state": {
                "sortOrder": "frequency",
                "showSearch": false,
                "searchQuery": ""
              },
              "icon": "lucide-archive",
              "title": "Todas as propriedades"
            }
          },
          {
            "id": "2c03e8af445011ad",
            "type": "leaf",
            "state": {
              "type": "outline",
              "state": {
                "followCursor": false,
                "showSearch": false,
                "searchQuery": ""
              },
              "icon": "lucide-list",
              "title": "Sumário"
            }
          }
        ]
      }
    ],
    "direction": "horizontal",
    "width": 300,
    "collapsed": true
  },
  "left-ribbon": {
    "hiddenItems": {
      "switcher:Abrir a troca rápida": false,
      "graph:Abrir visualização em gráfico": false,
      "canvas:Criar novo canvas": false,
      "daily-notes:Abrir a nota de hoje": false,
      "templates:Inserir modelo": false,
      "command-palette:Abrir paleta de comandos": false,
      "bases:Criar nova base": false
    }
  },
  "active": "3cf91371da09bdd5",
  "lastOpenFiles": [
    "Laboratorio/Projetos/Exemplo Arquitetura Tasks.md",
    "Laboratorio/Exemplos-API/Usuarios com API.md",
    "Laboratorio/Exemplos-API/Tarefas CRUD.md",
    "Laboratorio/Exemplos-API",
    "Conhecimento/Frontend/TypeScript/Type Guards.md",
    "Conhecimento/Frontend/TypeScript/Satisfies.md",
    "Conhecimento/Frontend/TypeScript/Discriminated Unions.md",
    "Conhecimento/Frontend/Testes/Testes Frontend.md",
    "Conhecimento/Frontend/Testes/Teste de Integracao.md",
    "Conhecimento/Frontend/Testes/Teste de Componente.md",
    "Conhecimento/Frontend/Testes/Teste Unitario.md",
    "Conhecimento/Frontend/Testes/Teste End to End.md",
    "Conhecimento/Frontend/Testes/O que Testar no Frontend.md",
    "Conhecimento/Frontend/Testes/Mocks e Fixtures.md",
    "Conhecimento/Frontend/Testes",
    "Conhecimento/Frontend/Tailwind/Variantes com clsx.md",
    "Conhecimento/Frontend/Tailwind/Tailwind Merge.md",
    "Conhecimento/Frontend/Tailwind/Dark Mode no Tailwind.md",
    "Conhecimento/Frontend/Seguranca/XSS.md",
    "Conhecimento/Frontend/Seguranca/Tokens no Frontend.md",
    "Conhecimento/Frontend/Seguranca/Seguranca Frontend.md",
    "Conhecimento/Frontend/Seguranca/LocalStorage vs Cookies.md",
    "Conhecimento/Frontend/Seguranca/Dependencias e Supply Chain.md",
    "Conhecimento/Frontend/Seguranca/Dados Sensiveis no Frontend.md",
    "Conhecimento/Frontend/Seguranca",
    "Conhecimento/Frontend/React/useReducer.md",
    "Conhecimento/Frontend/React/Hooks Customizados.md",
    "Conhecimento/Frontend/React/Context API.md",
    "Conhecimento/Frontend/Performance/Performance Frontend.md",
    "Conhecimento/Frontend/Performance",
    "Conhecimento/Frontend/Orientacao-a-Objetos",
    "Conhecimento/Frontend/Logica",
    "Conhecimento/Frontend/Estruturas-de-Dados",
    "Conhecimento/Frontend/Engenharia",
    "Conhecimento/Frontend/Debugging",
    "Conhecimento/Frontend/Dados",
    "Sem título 1.canvas",
    "Sem título.canvas"
  ]
}